{
    "type": "FeatureCollection",
    "features": [
      {
        "type": "Feature",
        "properties": {
          "name": "Chatterbox",
          "imgname":"images/race/stuntplane.jpg",
          "ptype": "Race"
        },
        "geometry": {
          "type": "Point",
          "coordinates": [41.928128, -17.503606]
        }
      },
      {
        "type": "Feature",
        "properties": {
          "name": "Container",
          "imgname":"images/race/ratoncanyon.jpg",
          "ptype": "Race"
        },
        "geometry": {
          "type": "Point",
          "coordinates": [34.848416, -55.675128]
        }
    },
    {
      "type": "Feature",
      "properties": {
        "name": "DOC Lab",
        "imgname":"images/race/ratoncanyon.jpg",
        "ptype": "Race"
      },
      "geometry": {
        "type": "Point",
        "coordinates": [33.03953159570298, -31.25284171104431]
      }
  },
  {
    "type": "Feature",
    "properties": {
      "name": "Elysian Lab",
      "imgname":"images/race/ratoncanyon.jpg",
      "ptype": "Race"
    },
    "geometry": {
      "type": "Point",
      "coordinates": [27.68868349835577, -55.82670497894287]
    }
}
  
    ]
  }
  